sice/__init__.py
sice/client.py
sice/resources/confirmacion.py
sice/resources/respuesta.py
sice/types.py
sice_python-0.1.0.dist-info/METADATA
sice_python-0.1.0.dist-info/WHEEL
sice_python-0.1.0.dist-info/RECORD
