Metadata-Version: 2.1
Name: sice-python
Version: 0.1.0
Summary: 
Author: tech
Author-email: tech@fondeadora.com
Requires-Python: >=3.7,<4.0
Classifier: Programming Language :: Python :: 3
Classifier: Programming Language :: Python :: 3.7
Classifier: Programming Language :: Python :: 3.8
Classifier: Programming Language :: Python :: 3.9
Classifier: Programming Language :: Python :: 3.10
Classifier: Programming Language :: Python :: 3.11
Classifier: Programming Language :: Python :: 3.12
Requires-Dist: cryptography (>=3.0,<40.1)
Requires-Dist: lxml (>=4.7.1,<5.0.0)
Requires-Dist: pydantic (>=1.8.2,<2.0.0)
Requires-Dist: requests (>=2.31.0,<3.0.0)
